nordvpn_polybar/__init__.py
nordvpn_polybar/main.py
nordvpn_polybar-0.0.4.dist-info/LICENSE.txt
nordvpn_polybar-0.0.4.dist-info/METADATA
nordvpn_polybar-0.0.4.dist-info/WHEEL
nordvpn_polybar-0.0.4.dist-info/top_level.txt
nordvpn_polybar-0.0.4.dist-info/RECORD
