Metadata-Version: 2.1
Name: nordvpn-polybar
Version: 0.0.4
Summary: Add a short description here!
Home-page: https://github.com/pyscaffold/pyscaffold/
Author: Kostas Vaggelakos
Author-email: kosta@vaggelakos.com
License: MIT
Project-URL: Documentation, https://pyscaffold.org/
Platform: any
Classifier: Development Status :: 4 - Beta
Classifier: Programming Language :: Python
License-File: LICENSE.txt
Requires-Dist: importlib-metadata ; python_version < "3.8"
Provides-Extra: testing
Requires-Dist: setuptools ; extra == 'testing'
Requires-Dist: pytest ; extra == 'testing'
Requires-Dist: pytest-cov ; extra == 'testing'
